{
  "type": "templates/SIMOS/Blueprint",
  "name": "Engine",
  "description": "This describes a engine",
  "attributes": [
    {
      "type": "string",
      "value": "",
      "name": "name"
    },
    {
      "type": "string",
      "value": "",
      "name": "power"
    },
    {
      "type": "templates/CarsDemo/subdir/subdir2/FuelPump",
      "name": "fuel_pump"
    }
  ],
  "storageRecipe": [
    {
      "name": "DefaultStorageRecipe",
      "type": "templates/SIMOS/StorageRecipe",
      "description": "",
      "attributes": [
        {
          "name": "fuel_pump",
          "contained": false
        }
      ]
    }
  ]
}
